{
  "disciplines": [
    {
      "name": {
        "en": "Animalism",
        "ru": "Анимализм"
      },
      "описание": "Используется теми, кто стремится к тесной сверхъестественной связи с животным миром, а также со Зверем самого вампира.",
      "кланы": [
        "Гангрел",
        "Носферату",
        "Равнос",
        "Цимисхи"
      ],
      "поддисциплины": [
        {
          "name": {
            "en": "Bond Famulus",
            "ru": "Бонд Фамулус"
          },
          "уровень": 1,
          "описание": "Создайте улучшенного животного-компаньона."
        },
        {
          "name": {
            "en": "Sense the Beast",
            "ru": "Чувствовать зверя"
          },
          "уровень": 1,
          "описание": "Чувствуйте враждебность и сверхъестественные черты."
        },
        {
          "name": {
            "en": "Animal Messenger",
            "ru": "Посланник животных"
          },
          "уровень": 2,
          "описание": "Используйте Famulus, чтобы отправить кому-нибудь сообщение."
        },
        {
          "name": {
            "en": "Atavism",
            "ru": "Атавизм"
          },
          "уровень": 2,
          "описание": "Верните животным их базовые и первобытные инстинкты."
        },
        {
          "name": {
            "en": "Feral Whispers",
            "ru": "Дикие шепоты"
          },
          "уровень": 2,
          "описание": "Двусторонняя связь с животными или вызов."
        },
        {
          "name": {
            "en": "Animal Succulence",
            "ru": "Сочные животные"
          },
          "уровень": 3,
          "описание": "Утолите дополнительный голод у животных, и сила крови будет на 2 уровня ниже в отношении штрафов за утоление."
        },
        {
          "name": {
            "en": "Augury",
            "ru": "предзнаменование"
          },
          "уровень": 3,
          "описание": "Заставьте рой сформировать ответ на вопрос."
        },
        {
          "name": {
            "en": "Awaken the Parasite",
            "ru": "Пробудить паразита"
          },
          "уровень": 3,
          "описание": "Пробуждайте жуков в теле жертвы."
        },
        {
          "name": {
            "en": "Messenger's Command",
            "ru": "Команда посланника"
          },
          "уровень": 3,
          "описание": "Используйте Принуждение или Загипнотизируйте через Фамулюса."
        },
        {
          "name": {
            "en": "Plague of Beasts",
            "ru": "Чума зверей"
          },
          "уровень": 3,
          "описание": "Отметьте особь как объект внимания животного."
        },
        {
          "name": {
            "en": "Quell the Beast",
            "ru": "Подавить зверя"
          },
          "уровень": 3,
          "описание": "Заставьте зверя вампира уснуть или сделайте смертного вялым."
        },
        {
          "name": {
            "en": "Scent of Prey",
            "ru": "Запах добычи"
          },
          "уровень": 3,
          "описание": "Выследите смертного, ставшего свидетелем нарушения маскарада."
        },
        {
          "name": {
            "en": "Unliving Hive",
            "ru": "Неживой улей"
          },
          "уровень": 3,
          "описание": "Распространяет влияние анимализма на стаи насекомых."
        },
        {
          "name": {
            "en": "Subsume the Spirit",
            "ru": "Подчинить дух"
          },
          "уровень": 4,
          "описание": "Обладать телом животного."
        },
        {
          "name": {
            "en": "Sway the Flock",
            "ru": "Раскачивайте стадо"
          },
          "уровень": 4,
          "описание": "Влияйте на животных на территории, чтобы они вели себя определенным образом."
        },
        {
          "name": {
            "en": "Animal Dominion",
            "ru": "Доминион животных"
          },
          "уровень": 5,
          "описание": "Командуйте стаями или стаями животных."
        },
        {
          "name": {
            "en": "Coax the Bestial Temper",
            "ru": "Укротить звериный характер"
          },
          "уровень": 5,
          "описание": "Увеличьте или уменьшите сложность сопротивления безумию для вампиров поблизости."
        },
        {
          "name": {
            "en": "Drawing Out the Beast",
            "ru": "Вытаскивание зверя"
          },
          "уровень": 5,
          "описание": "Перенесите свой ужас или ярость на ближайшую жертву."
        }
      ]
    },
    {
      "name": {
        "en": "Auspex",
        "ru": "Прорицание"
      },
      "описание": "Позволяет обострять физические и психические чувства, усиливая осведомленность, восприятие и даже давая видения будущего.",
      "кланы": [
        "Геката",
        "Малкавиан",
        "Салюбри",
        "Тореадор",
        "Тремер"
      ],
      "поддисциплины": [
        {
          "name": {
            "en": "Heightened Senses",
            "ru": "Обостренные чувства"
          },
          "уровень": 1,
          "описание": "Улучшите вампирические чувства и добавьте рейтинг Прорицания ко всем броскам восприятия."
        },
        {
          "name": {
            "en": "Sense the Unseen",
            "ru": "Почувствуйте невидимое"
          },
          "уровень": 1,
          "описание": "Ощутите сверхъестественную активность."
        },
        {
          "name": {
            "en": "Panacea Errata",
            "ru": "Панацея ошибок"
          },
          "уровень": 2,
          "описание": "Восстанавливает силу воли и успокаивает нервы."
        },
        {
          "name": {
            "en": "Premonition",
            "ru": "Предчувствие"
          },
          "уровень": 2,
          "описание": "Видения будущего."
        },
        {
          "name": {
            "en": "Reveal Temperament",
            "ru": "Раскрыть темперамент"
          },
          "уровень": 2,
          "описание": "Почувствуйте запах резонанса цели и/или присутствия Дискразии."
        },
        {
          "name": {
            "en": "Unerring Pursuit",
            "ru": "Безошибочное преследование"
          },
          "уровень": 2,
          "описание": "Отслеживание жертвы."
        },
        {
          "name": {
            "en": "Fatal Flaw",
            "ru": "Фатальный недостаток"
          },
          "уровень": 3,
          "описание": "Найдите слабое место цели"
        },
        {
          "name": {
            "en": "Haruspex",
            "ru": "Гаруспик"
          },
          "уровень": 3,
          "описание": "Используйте недавних мертвецов, чтобы перебросить кубики до конца ночи."
        },
        {
          "name": {
            "en": "Scry the Soul",
            "ru": "Увидеть душу"
          },
          "уровень": 3,
          "описание": "Воспринимает информацию о цели."
        },
        {
          "name": {
            "en": "Share the Senses",
            "ru": "Поделитесь чувствами"
          },
          "уровень": 3,
          "описание": "Задействование чувств других."
        },
        {
          "name": {
            "en": "Vermin Vision Errata",
            "ru": "Ошибки в зрении Vermin"
          },
          "уровень": 3,
          "описание": "Поделитесь чувствами с животными."
        },
        {
          "name": {
            "en": "Heart Laid Bare",
            "ru": "Обнаженное сердце"
          },
          "уровень": 4,
          "описание": "Узнайте самый глубокий страх или желание цели"
        },
        {
          "name": {
            "en": "Spirit's Touch",
            "ru": "Прикосновение духа"
          },
          "уровень": 4,
          "описание": "Сбор эмоционального остатка от объекта или места"
        },
        {
          "name": {
            "en": "Clairvoyance",
            "ru": "Ясновидение"
          },
          "уровень": 5,
          "описание": "Сбор информации из окружения"
        },
        {
          "name": {
            "en": "Possession",
            "ru": "Владение"
          },
          "уровень": 5,
          "описание": "Обладать смертным телом"
        },
        {
          "name": {
            "en": "Telepathy",
            "ru": "Телепатия"
          },
          "уровень": 5,
          "описание": "Читать мысли и проектировать мысли"
        },
        {
          "name": {
            "en": "Unburdening the Bestial Soul",
            "ru": "Освобождение звериной души"
          },
          "уровень": 5,
          "описание": "Удаление пятен или защита от пятен"
        }
      ]
    },
    {
      "name": {
        "en": "Blood Sorcery",
        "ru": "Кровавое колдовство"
      },
      "описание": "Тип магии крови, позволяющий практикам манипулировать кровью - как смертной, так и вампирской. Ритуалы Кровавого колдовства являются расширением этой дисциплины.",
      "кланы": [
        "Бану Хаким",
        "Тремер"
      ],
      "поддисциплины": [
        {
          "name": {
            "en": "A Taste for Blood",
            "ru": "Вкус крови"
          },
          "уровень": 1,
          "описание": "Откройте для себя черты другого человека через его кровь."
        },
        {
          "name": {
            "en": "Corrosive Vitae",
            "ru": "Коррозионное витэ"
          },
          "уровень": 1,
          "описание": "Сделайте витэ разъедающим."
        },
        {
          "name": {
            "en": "Shape the Sanguine Sacrament",
            "ru": "Формируйте таинство сангвиника"
          },
          "уровень": 1,
          "описание": "Придайте крови форму или изображение. Ошибки"
        },
        {
          "name": {
            "en": "Extinguish Vitae",
            "ru": "Погасить витэ"
          },
          "уровень": 2,
          "описание": "При использовании увеличивает «Голод» другого Сородича."
        },
        {
          "name": {
            "en": "Scour Secrets",
            "ru": "Секреты чистки"
          },
          "уровень": 2,
          "описание": "Просмотрите большое количество контента за считанные минуты. Ошибки"
        },
        {
          "name": {
            "en": "Blood of Potency",
            "ru": "Кровь Могущества"
          },
          "уровень": 3,
          "описание": "Временно повысьте эффективность крови."
        },
        {
          "name": {
            "en": "Ripples of the Heart",
            "ru": "Пульсация сердца"
          },
          "уровень": 3,
          "описание": "Манипулировать кровью или Кровью других."
        },
        {
          "name": {
            "en": "Scorpion’s Touch",
            "ru": "Прикосновение Скорпиона"
          },
          "уровень": 3,
          "описание": "Превратите собственное витэ в парализующий яд."
        },
        {
          "name": {
            "en": "Transitive Bond",
            "ru": "Переходная связь"
          },
          "уровень": 3,
          "описание": "Расширьте свойства Связи Крови в организме."
        },
        {
          "name": {
            "en": "Blood Aegis",
            "ru": "Кровавая эгида"
          },
          "уровень": 4,
          "описание": "Формируют защитный гематоэнцефалический барьер."
        },
        {
          "name": {
            "en": "Fulminating Vitae",
            "ru": "Молниеносное витэ"
          },
          "уровень": 4,
          "описание": "Бомба из банки витэ."
        },
        {
          "name": {
            "en": "Marionette",
            "ru": "Марионетка"
          },
          "уровень": 4,
          "описание": "Контролируйте кровь внутри тела, живого или мертвого."
        },
        {
          "name": {
            "en": "Theft of Vitae",
            "ru": "Кража Витэ"
          },
          "уровень": 4,
          "описание": "Манипулируйте кровью жертвы через воздух, чтобы накормить ее."
        },
        {
          "name": {
            "en": "Baal’s Caress",
            "ru": "Ласка Баала"
          },
          "уровень": 5,
          "описание": "Превратите собственное Витэ пользователя в агрессивный и смертельный яд."
        },
        {
          "name": {
            "en": "Cauldron of Blood",
            "ru": "Котел Крови"
          },
          "уровень": 5,
          "описание": "Вскипятите кровь жертвы в ее теле."
        },
        {
          "name": {
            "en": "Reclamation of Vitae",
            "ru": "Восстановление Витэ"
          },
          "уровень": 5,
          "описание": "Верните Кровь, полученную для создания гулей на расстоянии."
        }
      ]
    },
    {
      "name": {
        "en": "Celerity",
        "ru": "Стремительность"
      },
      "описание": "Усиливает подвижность пользователя, давая неестественную быстроту движений и сверхъестественные рефлексы.",
      "кланы": [
        "Бану Хаким",
        "Бруха",
        "Тореадор"
      ],
      "поддисциплины": [
        {
          "name": {
            "en": "Cat’s Grace",
            "ru": "Кошачья грация"
          },
          "уровень": 1,
          "описание": "Автоматически проходить тесты баланса."
        },
        {
          "name": {
            "en": "Rapid Reflexes",
            "ru": "Быстрые рефлексы"
          },
          "уровень": 1,
          "описание": "Более быстрые реакции и незначительные действия."
        },
        {
          "name": {
            "en": "Fleetness",
            "ru": "Быстрота"
          },
          "уровень": 2,
          "описание": "Добавьте рейтинг Стремительности для небоевой проверки Ловкости или защиты."
        },
        {
          "name": {
            "en": "Rush Job",
            "ru": "Срочная работа"
          },
          "уровень": 2,
          "описание": "Выполните задачу, связанную с навыком, которая займет много времени, за считанные секунды."
        },
        {
          "name": {
            "en": "A Thousand Cuts",
            "ru": "Тысяча сокращений"
          },
          "уровень": 3,
          "описание": "Добавьте Стремительность в Драку/Ближний бой, чтобы автоматически ослаблять смертных и превращать Сородичей в нарушение маскарада."
        },
        {
          "name": {
            "en": "Blink",
            "ru": "Мигать"
          },
          "уровень": 3,
          "описание": "Сокращает дистанцию, как будто телепортируется."
        },
        {
          "name": {
            "en": "Traversal",
            "ru": "Обход"
          },
          "уровень": 3,
          "описание": "Двигайтесь достаточно быстро, чтобы подниматься по вертикальным поверхностям или жидким поверхностям."
        },
        {
          "name": {
            "en": "Weaving",
            "ru": "Ткачество"
          },
          "уровень": 3,
          "описание": "Уберите штраф за уклонение от нескольких противников дальнего боя."
        },
        {
          "name": {
            "en": "Blurred Momentum",
            "ru": "Размытый импульс"
          },
          "уровень": 4,
          "описание": "Атаки на пользователя с меньшим успехом, чем его рейтинг Стремительности, промахиваются."
        },
        {
          "name": {
            "en": "Draught of Elegance",
            "ru": "Проект элегантности"
          },
          "уровень": 4,
          "описание": "Превратите их витэ в повышение стремительности для других."
        },
        {
          "name": {
            "en": "Unerring Aim",
            "ru": "Безошибочная цель"
          },
          "уровень": 4,
          "описание": "Мир замедляется до ползания"
        },
        {
          "name": {
            "en": "Unseen Strike",
            "ru": "Невидимый удар"
          },
          "уровень": 4,
          "описание": "Исчезайте, а затем снова появляйтесь, чтобы внезапно атаковать врага."
        },
        {
          "name": {
            "en": "Lightning Strike",
            "ru": "Удар молнии"
          },
          "уровень": 5,
          "описание": "Атака с молниеносной скоростью"
        },
        {
          "name": {
            "en": "Split Second",
            "ru": "Доля секунды"
          },
          "уровень": 5,
          "описание": "Изменить события, указанные Рассказчиком в текущей сцене, в пределах разумного."
        }
      ]
    },
    {
      "name": {
        "en": "Dominate",
        "ru": "Доминирование"
      },
      "описание": "Позволяет контролировать разум через зрительный контакт и произнесенное слово, а также изменять воспоминания жертв.",
      "кланы": [
        "Ласомбра",
        "Малкавиан",
        "Салюбри",
        "Тремер",
        "Цимисхи",
        "Вентру"
      ],
      "поддисциплины": [
        {
          "name": {
            "en": "Cloud Memory",
            "ru": "Облачная память"
          },
          "уровень": 1,
          "описание": "Заставьте кого-нибудь забыть текущий момент."
        },
        {
          "name": {
            "en": "Compel",
            "ru": "Заставить"
          },
          "уровень": 1,
          "описание": "Выдайте одну команду."
        },
        {
          "name": {
            "en": "Slavish Devotion",
            "ru": "Рабская преданность"
          },
          "уровень": 1,
          "описание": "Тем, кто уже находится под Доминированием, легче противостоять Доминированию других сородичей."
        },
        {
          "name": {
            "en": "Dementation",
            "ru": "Помешательство"
          },
          "уровень": 2,
          "описание": "Сводите других с ума."
        },
        {
          "name": {
            "en": "Domitor's Favor",
            "ru": "Благосклонность Домитора"
          },
          "уровень": 2,
          "описание": "Усложните неповиновение, находясь под узами крови."
        },
        {
          "name": {
            "en": "Mesmerize",
            "ru": "Гипнотизировать"
          },
          "уровень": 2,
          "описание": "Выдавайте сложные команды."
        },
        {
          "name": {
            "en": "The Stolen Voice",
            "ru": "Украденный голос"
          },
          "уровень": 2,
          "описание": "Лишите цель возможности выражать свои мысли. Невозможно говорить, писать или жестикулировать."
        },
        {
          "name": {
            "en": "Forgetful Mind",
            "ru": "Забывчивый разум"
          },
          "уровень": 3,
          "описание": "Переписать чью-то память."
        },
        {
          "name": {
            "en": "Submerged Directive",
            "ru": "Скрытая директива"
          },
          "уровень": 3,
          "описание": "Приказы «Имплантировать Доминирование» как предложения для жертв."
        },
        {
          "name": {
            "en": "Ancestral Dominion",
            "ru": "Родовой Доминион"
          },
          "уровень": 4,
          "описание": "Призывайте потомка действовать, даже если это противоречит его собственному мнению."
        },
        {
          "name": {
            "en": "Implant Suggestion",
            "ru": "Предложение по имплантации"
          },
          "уровень": 4,
          "описание": "Временно измените личность или мнение другого человека."
        },
        {
          "name": {
            "en": "Rationalize",
            "ru": "Рационализировать"
          },
          "уровень": 4,
          "описание": "Убедите жертв Доминирования, что это была их идея."
        },
        {
          "name": {
            "en": "Tabula Rasa",
            "ru": "Табула Раса"
          },
          "уровень": 4,
          "описание": "Сотрите память жертвы до такой степени, что она не будет знать, кто она."
        },
        {
          "name": {
            "en": "Mass Manipulation",
            "ru": "Массовое манипулирование"
          },
          "уровень": 5,
          "описание": "Распространите эффекты «Доминирования» на несколько целей."
        },
        {
          "name": {
            "en": "Terminal Decree",
            "ru": "Терминальный указ"
          },
          "уровень": 5,
          "описание": "Усиливайте эффекты Доминирования, чтобы обойти самосохранение жертвы."
        }
      ]
    },
    {
      "name": {
        "en": "Fortitude",
        "ru": "Стойкость"
      },
      "описание": "Укрепляет физическую и ментальную сопротивляемость пользователя.",
      "кланы": [
        "Гангрел",
        "Геката",
        "Салюбри",
        "Вентру"
      ],
      "поддисциплины": [
        {
          "name": {
            "en": "Resilience",
            "ru": "Устойчивость"
          },
          "уровень": 1,
          "описание": "Добавьте их рейтинг Стойкости к шкале здоровья."
        },
        {
          "name": {
            "en": "Unswayable Mind",
            "ru": "Непоколебимый разум"
          },
          "уровень": 1,
          "описание": "Добавьте рейтинг Стойкости к броскам, чтобы противостоять методам, повлиявшим на разум персонажа против его воли, включая сверхъестественные."
        },
        {
          "name": {
            "en": "Earth’s Perseverance",
            "ru": "Настойчивость Земли"
          },
          "уровень": 2,
          "описание": "Становится невозможно сдвинуться с этого места"
        },
        {
          "name": {
            "en": "Enduring Beasts",
            "ru": "Выносливые звери"
          },
          "уровень": 2,
          "описание": "Поделитесь силой вампира с животными."
        },
        {
          "name": {
            "en": "Invigorating Vitae",
            "ru": "Бодрящее витэ"
          },
          "уровень": 2,
          "описание": "Исцеляйте смертных быстрее с помощью Крови."
        },
        {
          "name": {
            "en": "Obdurate",
            "ru": "Упрямый"
          },
          "уровень": 2,
          "описание": "Сохраняйте равновесие при нанесении сильного удара."
        },
        {
          "name": {
            "en": "Toughness",
            "ru": "Прочность"
          },
          "уровень": 2,
          "описание": "Вычтите рейтинг Стойкости из всего поверхностного урона, полученного до его деления пополам, его нельзя округлить ниже единицы."
        },
        {
          "name": {
            "en": "Calloused Soul",
            "ru": "Мозолистая душа"
          },
          "уровень": 3,
          "описание": "Заблаговременно удалите пятна, чтобы предотвратить/уменьшить дальнейшее появление пятен."
        },
        {
          "name": {
            "en": "Defy Bane",
            "ru": "Бросить вызов Бэйну"
          },
          "уровень": 3,
          "описание": "Преобразуйте усиленные повреждения в поверхностные повреждения."
        },
        {
          "name": {
            "en": "Fortify the Inner Façade",
            "ru": "Укрепите внутренний фасад"
          },
          "уровень": 3,
          "описание": "Увеличение сложности умственных способностей читать или проникать в разум на половину рейтинга стойкости."
        },
        {
          "name": {
            "en": "Seal the Beast's Maw",
            "ru": "Запечатать пасть зверя"
          },
          "уровень": 3,
          "описание": "Вампир может игнорировать эффекты голода, если он не увеличивает голод за счет двух проверок пробуждения, но уменьшает запас кубиков."
        },
        {
          "name": {
            "en": "Valeren",
            "ru": "Валерен"
          },
          "уровень": 3,
          "описание": "Вылечите раненого вампира."
        },
        {
          "name": {
            "en": "Draught of Endurance",
            "ru": "Напиток выносливости"
          },
          "уровень": 4,
          "описание": "Превратите их витэ в повышение стойкости для других."
        },
        {
          "name": {
            "en": "Gorgon’s Scales",
            "ru": "Чешуя Горгоны"
          },
          "уровень": 4,
          "описание": "Резонансы дают Сородичам различные бонусы."
        },
        {
          "name": {
            "en": "Shatter",
            "ru": "Разбить"
          },
          "уровень": 4,
          "описание": "Противник получает урон, который вычитает Стойкость."
        },
        {
          "name": {
            "en": "Flesh of Marble",
            "ru": "Мраморная плоть"
          },
          "уровень": 5,
          "описание": "Игнорируйте первый источник физического урона каждый ход, кроме солнечного света."
        },
        {
          "name": {
            "en": "Meat Shields",
            "ru": "Мясные щиты"
          },
          "уровень": 5,
          "описание": "Увеличьте Стойкость на число, равное половине присутствующих слабых смертных. (Округлено вниз)"
        },
        {
          "name": {
            "en": "Prowess from Pain",
            "ru": "Доблесть от боли"
          },
          "уровень": 5,
          "описание": "Больше не получает штрафа за урон здоровью и может увеличивать один атрибут за каждый уровень урона на своем трекере."
        }
      ]
    },
    {
      "name": {
        "en": "Obfuscate",
        "ru": "Затемнение"
      },
      "описание": "Искусство быть незаметным даже в толпе: либо полностью исчезая из внимания, либо сливаясь с окружением.",
      "кланы": [
        "Бану Хаким",
        "Малкавиан",
        "Министерство",
        "Носферату",
        "Равнос"
      ],
      "поддисциплины": [
        {
          "name": {
            "en": "Cloak of Shadows",
            "ru": "Плащ теней"
          },
          "уровень": 1,
          "описание": "Пока пользователь стоит на месте, он сливается с окружающей средой."
        },
        {
          "name": {
            "en": "Silence of Death",
            "ru": "Молчание смерти"
          },
          "уровень": 1,
          "описание": "Сводит на нет звуки, издаваемые пользователем."
        },
        {
          "name": {
            "en": "Chimerstry",
            "ru": "Химерия"
          },
          "уровень": 2,
          "описание": "Создавайте краткие, но реалистичные галлюцинации."
        },
        {
          "name": {
            "en": "Doubletalk",
            "ru": "Двойной разговор"
          },
          "уровень": 2,
          "описание": "Говорите одно, а по секрету передайте другое."
        },
        {
          "name": {
            "en": "Ghost's Passing",
            "ru": "Прохождение призрака"
          },
          "уровень": 2,
          "описание": "Пользователь может применить затемнение к следам животного."
        },
        {
          "name": {
            "en": "Unseen Passage",
            "ru": "Невидимый проход"
          },
          "уровень": 2,
          "описание": "Теперь пользователь может двигаться, оставаясь скрытым."
        },
        {
          "name": {
            "en": "Ventriloquism",
            "ru": "Чревовещание"
          },
          "уровень": 2,
          "описание": "Подайте свой голос так, чтобы его мог услышать только предполагаемый получатель."
        },
        {
          "name": {
            "en": "Fata Morgana",
            "ru": "Фата Моргана"
          },
          "уровень": 3,
          "описание": "Сложные галлюцинации."
        },
        {
          "name": {
            "en": "Ghost in the Machine",
            "ru": "Призрак в машине"
          },
          "уровень": 3,
          "описание": "Позволяет передавать эффекты затемнения с помощью технологии при просмотре на живом экране."
        },
        {
          "name": {
            "en": "Guise of the Departed",
            "ru": "Облик ушедшего"
          },
          "уровень": 3,
          "описание": "Копируйте внешность и манеры недавно умершего смертного."
        },
        {
          "name": {
            "en": "Mask of Isolation",
            "ru": "Маска изоляции"
          },
          "уровень": 3,
          "описание": "Наденьте на жертву Маску Тысячи Лиц."
        },
        {
          "name": {
            "en": "Mask of a Thousand Faces",
            "ru": "Маска тысячи лиц"
          },
          "уровень": 3,
          "описание": "Сделайте так, чтобы они выглядели как обыденное лицо, а не исчезали, позволяя взаимодействовать и общаться."
        },
        {
          "name": {
            "en": "Mental Maze",
            "ru": "Ментальный лабиринт"
          },
          "уровень": 3,
          "описание": "Лишите жертву чувства направления и местоположения в определенной локации."
        },
        {
          "name": {
            "en": "Mind Masque",
            "ru": "Маска разума"
          },
          "уровень": 3,
          "описание": "Скрывайте и заменяйте эмоции и мысли против тех, кто желает прочитать их сверхъестественными средствами."
        },
        {
          "name": {
            "en": "Conceal",
            "ru": "Скрыть"
          },
          "уровень": 4,
          "описание": "Замаскируйте неодушевленный предмет."
        },
        {
          "name": {
            "en": "Seclusion",
            "ru": "Уединение"
          },
          "уровень": 4,
          "описание": "Цель не может видеть или слышать какое-либо другое существо, живое или неживое."
        },
        {
          "name": {
            "en": "Vanish",
            "ru": "Исчезновение"
          },
          "уровень": 4,
          "описание": "Активируйте «Плащ теней» или «Невидимый проход», пока за вами наблюдают."
        },
        {
          "name": {
            "en": "Cloak the Gathering",
            "ru": "Скрыть сбор"
          },
          "уровень": 5,
          "описание": "Укрытие компаньонов под затемнением."
        },
        {
          "name": {
            "en": "Impostor's Guise",
            "ru": "Облик самозванца"
          },
          "уровень": 5,
          "описание": "Появиться как кто-то другой."
        }
      ]
    },
    {
      "name": {
        "en": "Oblivion",
        "ru": "Забвение"
      },
      "описание": "Имеет две ветви: одна позволяет управлять тенями по воле пользователя, другая - использовать некромантию и духов; обе обращаются к Бездне. Церемонии Забвения являются расширением этой дисциплины.",
      "кланы": [
        "Геката",
        "Ласомбра"
      ],
      "поддисциплины": [
        {
          "name": {
            "en": "Ashes to Ashes",
            "ru": "Пепел к пеплу"
          },
          "уровень": 1,
          "описание": "Уничтожьте труп, растворив его."
        },
        {
          "name": {
            "en": "Binding Fetter",
            "ru": "Связывающие оковы"
          },
          "уровень": 1,
          "описание": "Позвольте пользователям иметь возможность идентифицировать оковы, используя свои чувства."
        },
        {
          "name": {
            "en": "Oblivion Sight",
            "ru": "Взгляд забвения"
          },
          "уровень": 1,
          "описание": "Ясно смотрите в темноте и различайте призраков."
        },
        {
          "name": {
            "en": "Shadow Cloak",
            "ru": "Теневой плащ"
          },
          "уровень": 1,
          "описание": "Бонус +2 к броскам на скрытность и запугиванию смертных."
        },
        {
          "name": {
            "en": "Arms of Ahriman",
            "ru": "Руки Аримана"
          },
          "уровень": 2,
          "описание": "Вызывает теневые придатки, которыми пользователь может управлять, но не может делать ничего другого."
        },
        {
          "name": {
            "en": "Fatal Precognition",
            "ru": "Фатальное предвидение"
          },
          "уровень": 2,
          "описание": "Видение смерти не-вампира."
        },
        {
          "name": {
            "en": "Fatal Prediction",
            "ru": "Фатальное предсказание"
          },
          "уровень": 2,
          "описание": "Увеличивает вероятность того, что смертному причинят вред внешние силы."
        },
        {
          "name": {
            "en": "Shadow Cast",
            "ru": "Отбрасывание тени"
          },
          "уровень": 2,
          "описание": "Создание теней от тела пользователя."
        },
        {
          "name": {
            "en": "Where the Veil Thins Errata",
            "ru": "Там, где тонет завеса, исправления"
          },
          "уровень": 2,
          "описание": "Определите плотность Плащаницы на их площади."
        },
        {
          "name": {
            "en": "Aura of Decay",
            "ru": "Аура разложения"
          },
          "уровень": 3,
          "описание": "Использование их связи с Обливионом может привести к увяданию растений, заболеваниям животных и людей, а также порче еды."
        },
        {
          "name": {
            "en": "Passion Feast",
            "ru": "Страстный праздник"
          },
          "уровень": 3,
          "описание": "Позволяет вампиру утолить голод страстью призраков."
        },
        {
          "name": {
            "en": "Shadow Perspective",
            "ru": "Теневая перспектива"
          },
          "уровень": 3,
          "описание": "Проецирует свои чувства в тень в пределах прямой видимости."
        },
        {
          "name": {
            "en": "Touch of Oblivion",
            "ru": "Прикосновение забвения"
          },
          "уровень": 3,
          "описание": "От прикосновения часть тела увядает."
        },
        {
          "name": {
            "en": "Necrotic Plague",
            "ru": "Некротическая чума"
          },
          "уровень": 4,
          "описание": "Проявляется болезнь у пострадавших."
        },
        {
          "name": {
            "en": "Stygian Shroud",
            "ru": "Стигийский саван"
          },
          "уровень": 4,
          "описание": "Тьма вырывается из ближайшей тени и окутывает область."
        },
        {
          "name": {
            "en": "Umbrous Clutch",
            "ru": "Темный клатч"
          },
          "уровень": 4,
          "описание": "Используя тень жертвы, они создают портал, бросая ее в руки пользователя."
        },
        {
          "name": {
            "en": "Shadow Step",
            "ru": "Теневой шаг"
          },
          "уровень": 5,
          "описание": "Пользователь может войти в одну тень и появиться в другой в пределах своего поля зрения."
        },
        {
          "name": {
            "en": "Skuld Fulfilled",
            "ru": "Скульд выполнен"
          },
          "уровень": 5,
          "описание": "Восстановите болезни, от которых кто-то выздоровел."
        },
        {
          "name": {
            "en": "Tenebrous Avatar",
            "ru": "Мрачный Аватар"
          },
          "уровень": 5,
          "описание": "Превращает свое тело в тень, способную перемещаться по любой поверхности или небольшим пространствам."
        },
        {
          "name": {
            "en": "Withering Spirit",
            "ru": "Увядающий дух"
          },
          "уровень": 5,
          "описание": "Разрушьте дух жертвы, пока она не превратится в оболочку."
        }
      ]
    },
    {
      "name": {
        "en": "Potence",
        "ru": "Могущество"
      },
      "описание": "Усиливает физическую мощь пользователя.",
      "кланы": [
        "Бруха",
        "Носферату",
        "Ласомбра"
      ],
      "поддисциплины": [
        {
          "name": {
            "en": "Lethal Body",
            "ru": "Смертельное тело"
          },
          "уровень": 1,
          "описание": "Атаки без оружия при использовании наносят смертным урон от обострения здоровья и игнорируют один уровень брони на каждый рейтинг Могущества пользователя."
        },
        {
          "name": {
            "en": "Soaring Leap",
            "ru": "Парящий прыжок"
          },
          "уровень": 1,
          "описание": "Прыжок выше и дальше, чем обычно."
        },
        {
          "name": {
            "en": "Prowess",
            "ru": "Доблесть"
          },
          "уровень": 2,
          "описание": "Добавьте рейтинг Могущества к их урону без оружия и к Силовым умениям, добавьте половину их рейтинга Могущества (округляя вверх) к урону в ближнем бою."
        },
        {
          "name": {
            "en": "Relentless Grasp",
            "ru": "Безжалостная хватка"
          },
          "уровень": 2,
          "описание": "Получите сверхъестественную силу хвата."
        },
        {
          "name": {
            "en": "Brutal Feed",
            "ru": "жестокий корм"
          },
          "уровень": 3,
          "описание": "Превратите кормление в жестокое и грязное занятие, которое длится всего несколько секунд, чтобы утолить голод пользователя."
        },
        {
          "name": {
            "en": "Spark of Rage",
            "ru": "Искра ярости"
          },
          "уровень": 3,
          "описание": "Пользователь может добавить свой рейтинг Могущества, чтобы раздражать или подстрекать человека или толпу к насильственным действиям."
        },
        {
          "name": {
            "en": "Uncanny Grip",
            "ru": "Странная хватка"
          },
          "уровень": 3,
          "описание": "Усиливает сцепление с большинством поверхностей, позволяя карабкаться или висеть без поддержки."
        },
        {
          "name": {
            "en": "Wrecker",
            "ru": "Саботажник"
          },
          "уровень": 3,
          "описание": "Двойной рейтинг могущества при использовании в силовых подвигах."
        },
        {
          "name": {
            "en": "Crash Down",
            "ru": "Крах вниз"
          },
          "уровень": 4,
          "описание": "Нанесите урон небольшой области при использовании «Парящего прыжка»."
        },
        {
          "name": {
            "en": "Draught of Might",
            "ru": "Настой мощи"
          },
          "уровень": 4,
          "описание": "Превратите их витэ в усиление Могущества для других."
        },
        {
          "name": {
            "en": "Earth Shock",
            "ru": "Земной шок"
          },
          "уровень": 5,
          "описание": "Создайте ударную волну, чтобы сбить противников с ног."
        },
        {
          "name": {
            "en": "Fist of Caine",
            "ru": "Кулак Каина"
          },
          "уровень": 5,
          "описание": "Наносит усиленный урон здоровью как смертным, так и сверхъестественным существам."
        },
        {
          "name": {
            "en": "Subtle Hammer",
            "ru": "Тонкий молот"
          },
          "уровень": 5,
          "описание": "Проецируйте силу вампира в определенную часть тела."
        }
      ]
    },
    {
      "name": {
        "en": "Presence",
        "ru": "Величие"
      },
      "описание": "Позволяет тонко манипулировать, контролировать и направлять эмоции окружающих к нужной цели.",
      "кланы": [
        "Бруха",
        "Равнос",
        "Тореадор",
        "Министерство",
        "Вентру"
      ],
      "поддисциплины": [
        {
          "name": {
            "en": "Awe",
            "ru": "Трепет"
          },
          "уровень": 1,
          "описание": "Добавьте рейтинг Присутствия к любому броску Навыка, включающему броски, связанные с Убеждением, Исполнением или Харизмой, по усмотрению ST."
        },
        {
          "name": {
            "en": "Daunt",
            "ru": "Даунт"
          },
          "уровень": 1,
          "описание": "Добавляйте рейтинг Присутствия к любым броскам на запугивание."
        },
        {
          "name": {
            "en": "Eyes of the Serpent",
            "ru": "Глаза Змеи"
          },
          "уровень": 1,
          "описание": "Обездвижьте жертву, установив зрительный контакт."
        },
        {
          "name": {
            "en": "Lingering Kiss",
            "ru": "Затяжной поцелуй"
          },
          "уровень": 2,
          "описание": "Можно использовать во время кормления, жертва получает бонус к социальному атрибуту на одну ночь."
        },
        {
          "name": {
            "en": "Melpominee",
            "ru": "Мельпомини"
          },
          "уровень": 2,
          "описание": "Используйте «Присутствие», не видя цели, а только находясь в пределах слышимости."
        },
        {
          "name": {
            "en": "Clear the Field",
            "ru": "Очистить поле"
          },
          "уровень": 3,
          "описание": "Освободите пространство спокойно и организованно."
        },
        {
          "name": {
            "en": "Dread Gaze",
            "ru": "Ужасающий взгляд"
          },
          "уровень": 3,
          "описание": "Вселяйте страх в цель, чтобы заставить ее бежать."
        },
        {
          "name": {
            "en": "Entrancement",
            "ru": "вход"
          },
          "уровень": 3,
          "описание": "Ввести кого-то в состояние восторга или обмана, когда он сделает все возможное, чтобы пользователь был доволен. Добавление рейтинга Присутствия на кубиках к любым социальным броскам против жертвы."
        },
        {
          "name": {
            "en": "Thrown Voice",
            "ru": "Брошенный голос"
          },
          "уровень": 3,
          "описание": "Направьте свой голос из любой точки видимости и оставьте голос там."
        },
        {
          "name": {
            "en": "True Love's Face",
            "ru": "Лицо настоящей любви"
          },
          "уровень": 3,
          "описание": "Жертва будет воспринимать пользователя как смертного, с которым у него сильная эмоциональная связь, будь то ненависть или любовь."
        },
        {
          "name": {
            "en": "Irresistible Voice",
            "ru": "Неотразимый голос"
          },
          "уровень": 4,
          "описание": "Одного голоса пользователя достаточно, чтобы использовать «Доминирование» на цели."
        },
        {
          "name": {
            "en": "Magnum Opus",
            "ru": "Магнум Опус"
          },
          "уровень": 4,
          "описание": "Внесение присутствия в произведение искусства."
        },
        {
          "name": {
            "en": "Suffuse the Edifice",
            "ru": "Наполните здание"
          },
          "уровень": 4,
          "описание": "Распространите присутствие на здание."
        },
        {
          "name": {
            "en": "Summon",
            "ru": "Вызвать"
          },
          "уровень": 4,
          "описание": "Призовите к себе кого-нибудь, к кому применили определенные силы Присутствия или кто попробовал витэ пользователя."
        },
        {
          "name": {
            "en": "Wingman",
            "ru": "ведомый"
          },
          "уровень": 4,
          "описание": "Распространите Присутствие на другого персонажа для использования."
        },
        {
          "name": {
            "en": "Majesty",
            "ru": "Величество"
          },
          "уровень": 5,
          "описание": "Каждый, кто смотрит на пользователя, ошарашен и не может действовать иначе, как в целях самосохранения."
        },
        {
          "name": {
            "en": "Star Magnetism",
            "ru": "Звездный магнетизм"
          },
          "уровень": 5,
          "описание": "Позволяет использовать функцию присутствия с помощью технологии прямой трансляции, не работает с записанным контентом."
        }
      ]
    },
    {
      "name": {
        "en": "Protean",
        "ru": "Протеизм"
      },
      "описание": "Дает способность менять форму, отращивать когти, сливаться с землей или превращаться в туман.",
      "кланы": [
        "Гангрел",
        "Министерство",
        "Цимисхи"
      ],
      "поддисциплины": [
        {
          "name": {
            "en": "Eyes of the Beast",
            "ru": "Глаза зверя"
          },
          "уровень": 1,
          "описание": "Позволяет пользователю видеть в полной темноте."
        },
        {
          "name": {
            "en": "Weight of the Feather",
            "ru": "Вес пера"
          },
          "уровень": 1,
          "описание": "Пользователь может сделать себя почти невесомым."
        },
        {
          "name": {
            "en": "Feral Weapons",
            "ru": "Дикое оружие"
          },
          "уровень": 2,
          "описание": "Удлините ногти пользователя в когти, получив модификатор +2 к повреждению или удлинению клыков и не получая штрафного штрафа за выстрел."
        },
        {
          "name": {
            "en": "Serpent's Kiss",
            "ru": "Змеиный поцелуй"
          },
          "уровень": 2,
          "описание": "Кусая кого-то, впрыскивайте в него его собственное витэ."
        },
        {
          "name": {
            "en": "The False Sip",
            "ru": "Ложный глоток"
          },
          "уровень": 2,
          "описание": "Не допускайте попадания крови или Крови в их систему."
        },
        {
          "name": {
            "en": "Vicissitude",
            "ru": "Превратность"
          },
          "уровень": 2,
          "описание": "Лепите плоть тел, позволяя изменять их собственные тела."
        },
        {
          "name": {
            "en": "Earth Meld",
            "ru": "Слияние Земли"
          },
          "уровень": 3,
          "описание": "Погрузитесь в землю и станьте единым целым с почвой."
        },
        {
          "name": {
            "en": "Fleshcrafting",
            "ru": "Создание плоти"
          },
          "уровень": 3,
          "описание": "Распространяет власть над плотью для использования на других."
        },
        {
          "name": {
            "en": "Shapechange",
            "ru": "Изменение формы"
          },
          "уровень": 3,
          "описание": "Превратитесь в животное с аналогичной массой тела."
        },
        {
          "name": {
            "en": "Visceral Absorption",
            "ru": "Висцеральное поглощение"
          },
          "уровень": 3,
          "описание": "Подтяните остатки крови и тела вампира, чтобы зачистить место происшествия."
        },
        {
          "name": {
            "en": "Horrid Form",
            "ru": "Ужасная форма"
          },
          "уровень": 4,
          "описание": "Примите чудовищную форму."
        },
        {
          "name": {
            "en": "Metamorphosis",
            "ru": "Метаморфоза"
          },
          "уровень": 4,
          "описание": "Расширяет возможность изменения формы, позволяя превращаться в животное, большее, чем масса вампира."
        },
        {
          "name": {
            "en": "Mist Form",
            "ru": "Туманная форма"
          },
          "уровень": 5,
          "описание": "Превратиться в облако тумана."
        },
        {
          "name": {
            "en": "One with the Land",
            "ru": "Один с землей"
          },
          "уровень": 5,
          "описание": "Погрузитесь в землю своих Доменов."
        },
        {
          "name": {
            "en": "The Heart of Darkness",
            "ru": "Сердце Тьмы"
          },
          "уровень": 5,
          "описание": "Позволяет вампиру извлечь собственное сердце и хранить его вне тела."
        },
        {
          "name": {
            "en": "The Unfettered Heart",
            "ru": "Свободное сердце"
          },
          "уровень": 5,
          "описание": "Сердце вампира может свободно перемещаться внутри сундука, что усложняет задачу."
        }
      ]
    },
    {
      "name": {
        "en": "Thin-blood Alchemy",
        "ru": "Тонкокровная алхимия"
      },
      "описание": "Создание смесей из крови, эмоций и других ингредиентов для активации уникальных эффектов и даже имитации других дисциплин.",
      "кланы": [
        "Тонкокровные"
      ],
      "поддисциплины": [
        {
          "name": {
            "en": "Far Reach",
            "ru": "Дальний предел"
          },
          "уровень": 1,
          "описание": "Толкайте, тяните, удерживайте или хватайте предметы или людей силой мысли."
        },
        {
          "name": {
            "en": "Gaoler's Bane",
            "ru": "Проклятие тюремщика"
          },
          "уровень": 1,
          "описание": "Получите бонус в 2 кубика, освободившись от физических ограничений или захватов."
        },
        {
          "name": {
            "en": "Haze",
            "ru": "Туман"
          },
          "уровень": 1,
          "описание": "Создайте туман, который следует за пользователем, что затрудняет его стрельбу или идентификацию."
        },
        {
          "name": {
            "en": "Mercurian Tongue",
            "ru": "Меркурианский язык"
          },
          "уровень": 1,
          "описание": "Говорить на других языках, кроме своего."
        },
        {
          "name": {
            "en": "Plug-In",
            "ru": "Плагин"
          },
          "уровень": 1,
          "описание": "Вырабатывают слабый электрический ток своим телом."
        },
        {
          "name": {
            "en": "Portable Shade",
            "ru": "Портативная тень"
          },
          "уровень": 1,
          "описание": "Выдерживать воздействие солнечного света и гулять на солнце."
        },
        {
          "name": {
            "en": "Blood of Mandagloire",
            "ru": "Кровь Мандаглуара"
          },
          "уровень": 2,
          "описание": "Заразите кровь стада, чтобы те, кто питается ею, погрузились в сон без сновидений."
        },
        {
          "name": {
            "en": "Counterfeit Discipline",
            "ru": "Поддельная дисциплина"
          },
          "уровень": 2,
          "описание": "Подделать дисциплину с одной точкой"
        },
        {
          "name": {
            "en": "Envelop",
            "ru": "Конверт"
          },
          "уровень": 2,
          "описание": "Создайте туман, который прилипнет к жертве."
        },
        {
          "name": {
            "en": "Friends List",
            "ru": "Список друзей"
          },
          "уровень": 2,
          "описание": "Увидеть связи между Сородичами и смертными"
        },
        {
          "name": {
            "en": "Mirror of Trust",
            "ru": "Зеркало доверия"
          },
          "уровень": 2,
          "описание": "Получите 3 дополнительных кубика, чтобы убедить или запугать кого-нибудь и заставить его быть честным."
        },
        {
          "name": {
            "en": "Red's Flaming Hot Sauce",
            "ru": "Пылающий острый соус Red's"
          },
          "уровень": 2,
          "описание": "Создайте сверхъестественный коктейль Молотова."
        },
        {
          "name": {
            "en": "Chemically-Induced Flashback",
            "ru": "Химически вызванное воспоминание"
          },
          "уровень": 3,
          "описание": "Наполните и испытайте Воспоминание о другом вампире."
        },
        {
          "name": {
            "en": "Concoct Ashe",
            "ru": "Придумать Эша"
          },
          "уровень": 3,
          "описание": "Создайте Эша из останков вампира."
        },
        {
          "name": {
            "en": "Counterfeit Discipline",
            "ru": "Поддельная дисциплина"
          },
          "уровень": 3,
          "описание": "Подделать двухточечную дисциплину"
        },
        {
          "name": {
            "en": "Defractionate",
            "ru": "дефракционировать"
          },
          "уровень": 3,
          "описание": "Превратите консервированную кровь в нечто вкусное для любого сородича."
        },
        {
          "name": {
            "en": "Fang-Stinger",
            "ru": "Клык-Стингер"
          },
          "уровень": 3,
          "описание": "Ввести в смертного кровь, которая не причинит ему вреда, но причинит вред вампирам, которые питаются от него."
        },
        {
          "name": {
            "en": "Freezer Fluid",
            "ru": "Морозильная жидкость"
          },
          "уровень": 3,
          "описание": "Заморозить тело вампира."
        },
        {
          "name": {
            "en": "Mandagloire",
            "ru": "Мандаглуар"
          },
          "уровень": 3,
          "описание": "Выпускает газ, вызывающий твердый паралич у смертных и сверхъестественных существ."
        },
        {
          "name": {
            "en": "On-Demand Sunburn",
            "ru": "Загар по требованию"
          },
          "уровень": 3,
          "описание": "Станьте солнечной батареей и наносите вред вампирам, которых они касаются."
        },
        {
          "name": {
            "en": "Profane Hieros Gamos",
            "ru": "Нечестивый Иерос Гамос"
          },
          "уровень": 3,
          "описание": "Измените их форму в идеальную человеческую форму."
        },
        {
          "name": {
            "en": "Rumor",
            "ru": "Слух"
          },
          "уровень": 3,
          "описание": "Сделайте заявление и убедите одного человека согласиться."
        },
        {
          "name": {
            "en": "Stay the Falling Sand",
            "ru": "Оставайся падающим песком"
          },
          "уровень": 3,
          "описание": "Медленное время"
        },
        {
          "name": {
            "en": "Tank",
            "ru": "Танк"
          },
          "уровень": 3,
          "описание": "Усилить их устойчивость к повреждениям"
        },
        {
          "name": {
            "en": "Airborne Momentum",
            "ru": "Воздушный импульс"
          },
          "уровень": 4,
          "описание": "Достичь полета"
        },
        {
          "name": {
            "en": "Counterfeit Discipline",
            "ru": "Поддельная дисциплина"
          },
          "уровень": 4,
          "описание": "Подделать трехточечную Дисциплину"
        },
        {
          "name": {
            "en": "Discipline Channeling",
            "ru": "Дисциплина"
          },
          "уровень": 4,
          "описание": "Наделите Эша дисциплинами"
        },
        {
          "name": {
            "en": "Hollow Leg",
            "ru": "Полая нога"
          },
          "уровень": 4,
          "описание": "Отравить другого Сородича, чтобы он не смог утолить голод."
        },
        {
          "name": {
            "en": "Short Circuit",
            "ru": "Короткое замыкание"
          },
          "уровень": 4,
          "описание": "Перегрузите аккумуляторы в электронике или электрооборудовании."
        },
        {
          "name": {
            "en": "Toxic Personality",
            "ru": "Токсичная личность"
          },
          "уровень": 4,
          "описание": "Выделяют из своих пор и отверстий едкую желчь."
        },
        {
          "name": {
            "en": "Awaken the Sleeper",
            "ru": "Разбудить спящего"
          },
          "уровень": 5,
          "описание": "Пробудить вампира от оцепенения"
        },
        {
          "name": {
            "en": "Counterfeit Discipline",
            "ru": "Поддельная дисциплина"
          },
          "уровень": 5,
          "описание": "Подделать четырехточечную Дисциплину"
        },
        {
          "name": {
            "en": "Flowering Amaranth",
            "ru": "Цветущий амарант"
          },
          "уровень": 5,
          "описание": "Поделитесь диаблери с другими тонкокровками."
        },
        {
          "name": {
            "en": "Moment of Clarity",
            "ru": "Момент ясности"
          },
          "уровень": 5,
          "описание": "Используйте силу Зверя, чтобы поддержать их."
        }
      ]
    },
    {
      "name": {
        "en": "Umbrakinesis",
        "ru": "??????????"
      },
      "????????": "?????????? ?????? ? ?? ????????????.",
      "?????": [],
      "?????????????": [
        {
          "name": {
            "en": "Veil Step",
            "ru": "??? ?????? ??????"
          },
          "???????": 2,
          "????????": "???????? ??? ????? ????????, ?????????? ???????????."
        }
      ]
    },
    {
      "name": {
        "en": "Hematurgy",
        "ru": "??????????"
      },
      "????????": "??????????? ?????? ? ?? ??????????.",
      "?????": [],
      "?????????????": [
        {
          "name": {
            "en": "Sanguine Lattice",
            "ru": "???????? ???????"
          },
          "???????": 4,
          "????????": "????????? ????????? ?? ?????, ???????????? ????."
        },
        {
          "name": {
            "en": "Crimson Tide",
            "ru": "???????? ??????"
          },
          "???????": 3,
          "????????": "????? ?????, ??????????? ? ??????????? ??????????."
        }
      ]
    },
    {
      "name": {
        "en": "Aethercraft",
        "ru": "??????????"
      },
      "????????": "???????? ??????? ??????? ? ???????? ??????.",
      "?????": [],
      "?????????????": [
        {
          "name": {
            "en": "Starbind",
            "ru": "???????? ???"
          },
          "???????": 1,
          "????????": "??????????? ??????????????? ?????, ???????????? ????."
        }
      ]
    }
  ]
}